NiukeQichexingyeMingqiBiMianshiXiaozhaoQiuzhiGonglve20212022Fix1/README.md
NiukeQichexingyeMingqiBiMianshiXiaozhaoQiuzhiGonglve20212022Fix1/__init__.py
NiukeQichexingyeMingqiBiMianshiXiaozhaoQiuzhiGonglve20212022Fix1/__main__.py
NiukeQichexingyeMingqiBiMianshiXiaozhaoQiuzhiGonglve20212022Fix1/file.epub
NiukeQichexingyeMingqiBiMianshiXiaozhaoQiuzhiGonglve20212022Fix1/index.html
NiukeQichexingyeMingqiBiMianshiXiaozhaoQiuzhiGonglve20212022Fix1/css/__init__.py
NiukeQichexingyeMingqiBiMianshiXiaozhaoQiuzhiGonglve20212022Fix1/css/annotations.css
NiukeQichexingyeMingqiBiMianshiXiaozhaoQiuzhiGonglve20212022Fix1/css/main.css
NiukeQichexingyeMingqiBiMianshiXiaozhaoQiuzhiGonglve20212022Fix1/css/normalize.css
NiukeQichexingyeMingqiBiMianshiXiaozhaoQiuzhiGonglve20212022Fix1/css/popup.css
NiukeQichexingyeMingqiBiMianshiXiaozhaoQiuzhiGonglve20212022Fix1/font/__init__.py
NiukeQichexingyeMingqiBiMianshiXiaozhaoQiuzhiGonglve20212022Fix1/font/fontello.eot
NiukeQichexingyeMingqiBiMianshiXiaozhaoQiuzhiGonglve20212022Fix1/font/fontello.svg
NiukeQichexingyeMingqiBiMianshiXiaozhaoQiuzhiGonglve20212022Fix1/font/fontello.ttf
NiukeQichexingyeMingqiBiMianshiXiaozhaoQiuzhiGonglve20212022Fix1/font/fontello.woff
NiukeQichexingyeMingqiBiMianshiXiaozhaoQiuzhiGonglve20212022Fix1/img/__init__.py
NiukeQichexingyeMingqiBiMianshiXiaozhaoQiuzhiGonglve20212022Fix1/img/annotator-glyph-sprite.png
NiukeQichexingyeMingqiBiMianshiXiaozhaoQiuzhiGonglve20212022Fix1/img/annotator-icon-sprite.png
NiukeQichexingyeMingqiBiMianshiXiaozhaoQiuzhiGonglve20212022Fix1/img/apple-touch-icon.png
NiukeQichexingyeMingqiBiMianshiXiaozhaoQiuzhiGonglve20212022Fix1/img/cancelfullscreen.png
NiukeQichexingyeMingqiBiMianshiXiaozhaoQiuzhiGonglve20212022Fix1/img/close.png
NiukeQichexingyeMingqiBiMianshiXiaozhaoQiuzhiGonglve20212022Fix1/img/fullscreen.png
NiukeQichexingyeMingqiBiMianshiXiaozhaoQiuzhiGonglve20212022Fix1/img/loader.gif
NiukeQichexingyeMingqiBiMianshiXiaozhaoQiuzhiGonglve20212022Fix1/img/menu-icon.png
niuke_qichexingye_mingqi_bi_mianshi_xiaozhao_qiuzhi_gonglve_2021_2022_fix1-2025.3.25.0.dist-info/METADATA
niuke_qichexingye_mingqi_bi_mianshi_xiaozhao_qiuzhi_gonglve_2021_2022_fix1-2025.3.25.0.dist-info/WHEEL
niuke_qichexingye_mingqi_bi_mianshi_xiaozhao_qiuzhi_gonglve_2021_2022_fix1-2025.3.25.0.dist-info/entry_points.txt
niuke_qichexingye_mingqi_bi_mianshi_xiaozhao_qiuzhi_gonglve_2021_2022_fix1-2025.3.25.0.dist-info/top_level.txt
niuke_qichexingye_mingqi_bi_mianshi_xiaozhao_qiuzhi_gonglve_2021_2022_fix1-2025.3.25.0.dist-info/RECORD
